dlprepare/__init__.py
dlprepare/csv_utils.py
dlprepare/tpu.py
dlprepare-0.0.2.dist-info/LICENSE
dlprepare-0.0.2.dist-info/METADATA
dlprepare-0.0.2.dist-info/WHEEL
dlprepare-0.0.2.dist-info/top_level.txt
dlprepare-0.0.2.dist-info/RECORD
