Metadata-Version: 2.1
Name: dlprepare
Version: 0.0.2
Summary: A data preparetion package for deep learning.
Home-page: https://gitlab.com/motkeg/Dlprepare
Author: Moti Gadian
Author-email: motkeg@gmail.com
License: UNKNOWN
Keywords: deep-learning,data preparetion,tensorflow
Platform: UNKNOWN
Classifier: Programming Language :: Python :: 3
Classifier: License :: OSI Approved :: MIT License
Classifier: Operating System :: OS Independent
Requires-Dist: pandas
Requires-Dist: scikit-learn
Requires-Dist: tensorflow
